{"web":{"client_id":"499021342163-1208142auv7p6cshejdhjogicam52eo8.apps.googleusercontent.com","project_id":"easy-list-470600","auth_uri":"https://accounts.google.com/o/oauth2/auth","token_uri":"https://oauth2.googleapis.com/token","auth_provider_x509_cert_url":"https://www.googleapis.com/oauth2/v1/certs","client_secret":"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","redirect_uris":["http://localhost:5173","http://localhost:5173/auth/callback","http://localhost:5173/auth/google/callback"],"javascript_origins":["http://localhost","http://localhost:5173","http://localhost:3000"]}}